Workbook

Sheet Start here
A1: Money Map: start here
A2: A 10-minute setup, then 5 minutes a week.
A4: 1. Dashboard: type your monthly take-home income and savings goal in the green cells.
A5: 2. Budget: adjust the Planned column to your life. Type Actual amounts as the month goes; each line turns green (OK) or red (Over).
A6: 3. Subscriptions: list every recurring charge. Mark Keep? = No for the ones you will cancel; the sheet shows what that saves per year.
A7: 4. Debt: list balances, APR and what you pay each month. Payoff order = avalanche (highest rate first). The Dashboard shows an approximate debt-free date.
A8: 5. NetWorth: list accounts. Net worth = assets minus the Debt tab.
A9: 6. Log: at month end, copy Income, Spending and Net worth into the row for that month to build your trend.
A11: Google Sheets: File > Import > Upload this file > 'Replace spreadsheet'. Formulas, dropdowns and colors carry over.
A12: Excel: opens directly. Numbers (Mac): opens with formulas; charts may look different.
A14: Green cells are inputs. Everything else is a formula; if you overwrite one by accident, undo (Ctrl/Cmd+Z).
A15: Questions or a broken formula? Message the shop and you get a fixed copy within a day.

Sheet Dashboard
A1: Money Map
A2: Fill the green cells on the other tabs. Everything here updates itself.
A4: Monthly take-home income | B4: 5200
A5: Savings goal (% of income) | B5: 0.2
A6: Emergency fund target (months of expenses) | B6: 3
A8: This month | D8: Spending by category
D9: Category | E9: Actual
A10: Actual spending | B10: =SUM(Budget!D5:D34) | D10: =Budget!A5 | E10: =Budget!D5
A11: Left to spend | B11: =B4-B10 | D11: =Budget!A6 | E11: =Budget!D6
A12: Subscriptions per month | B12: =Subscriptions!H3 | D12: =Budget!A7 | E12: =Budget!D7
A13: Subscriptions per year | B13: =Subscriptions!H4 | D13: =Budget!A8 | E13: =Budget!D8
A14: Savings this month | B14: =B4-B10 | D14: =Budget!A9 | E14: =Budget!D9
A15: Savings rate | B15: =IF(B4=0,0,B14/B4) | D15: =Budget!A10 | E15: =Budget!D10
A16: Savings goal | B16: =B4*B5 | D16: =Budget!A11 | E16: =Budget!D11
A17: On track? | B17: =IF(B14>=B16,"Yes","No, short by "&TEXT(B16-B14,"$#,##0")) | D17: =Budget!A12 | E17: =Budget!D12
A18: Emergency fund target | B18: =B9*B6 | D18: =Budget!A13 | E18: =Budget!D13
A19: Total debt | B19: =Debt!G3 | D19: =Budget!A14 | E19: =Budget!D14
A20: Debt-free date (avalanche) | B20: =Debt!G6
A21: Net worth | B21: =NetWorth!D3

Sheet Budget
A1: Monthly budget
A2: Green = you type. Planned vs actual, with the difference and a status per line.
A4: Category | B4: Notes | C4: Planned | D4: Actual | E4: Difference | F4: Status
A5: Rent / mortgage | C5: 1800 | D5: 0 | E5: =C5-D5 | F5: =IF(D5=0,"",IF(D5>C5,"Over","OK"))
A6: Utilities | C6: 180 | D6: 0 | E6: =C6-D6 | F6: =IF(D6=0,"",IF(D6>C6,"Over","OK"))
A7: Groceries | C7: 450 | D7: 0 | E7: =C7-D7 | F7: =IF(D7=0,"",IF(D7>C7,"Over","OK"))
A8: Dining out | C8: 220 | D8: 0 | E8: =C8-D8 | F8: =IF(D8=0,"",IF(D8>C8,"Over","OK"))
A9: Transport | C9: 160 | D9: 0 | E9: =C9-D9 | F9: =IF(D9=0,"",IF(D9>C9,"Over","OK"))
A10: Phone + internet | C10: 110 | D10: 0 | E10: =C10-D10 | F10: =IF(D10=0,"",IF(D10>C10,"Over","OK"))
A11: Insurance | C11: 140 | D11: 0 | E11: =C11-D11 | F11: =IF(D11=0,"",IF(D11>C11,"Over","OK"))
A12: Health | C12: 90 | D12: 0 | E12: =C12-D12 | F12: =IF(D12=0,"",IF(D12>C12,"Over","OK"))
A13: Subscriptions | C13: =Subscriptions!H3 | D13: 0 | E13: =C13-D13 | F13: =IF(D13=0,"",IF(D13>C13,"Over","OK"))
A14: Fun | C14: 150 | D14: 0 | E14: =C14-D14 | F14: =IF(D14=0,"",IF(D14>C14,"Over","OK"))
A15: Clothing | C15: 60 | D15: 0 | E15: =C15-D15 | F15: =IF(D15=0,"",IF(D15>C15,"Over","OK"))
A16: Gifts | C16: 40 | D16: 0 | E16: =C16-D16 | F16: =IF(D16=0,"",IF(D16>C16,"Over","OK"))
A17: Savings transfer | C17: 800 | D17: 0 | E17: =C17-D17 | F17: =IF(D17=0,"",IF(D17>C17,"Over","OK"))
A18: Debt payments | C18: =Debt!G4 | D18: 0 | E18: =C18-D18 | F18: =IF(D18=0,"",IF(D18>C18,"Over","OK"))
A19: Other | C19: 100 | D19: 0 | E19: =C19-D19 | F19: =IF(D19=0,"",IF(D19>C19,"Over","OK"))
E20: =IF(OR(C20<>"",D20<>""),C20-D20,"") | F20: =IF(D20="","",IF(D20>C20,"Over","OK"))
E21: =IF(OR(C21<>"",D21<>""),C21-D21,"") | F21: =IF(D21="","",IF(D21>C21,"Over","OK"))
E22: =IF(OR(C22<>"",D22<>""),C22-D22,"") | F22: =IF(D22="","",IF(D22>C22,"Over","OK"))
E23: =IF(OR(C23<>"",D23<>""),C23-D23,"") | F23: =IF(D23="","",IF(D23>C23,"Over","OK"))
E24: =IF(OR(C24<>"",D24<>""),C24-D24,"") | F24: =IF(D24="","",IF(D24>C24,"Over","OK"))
E25: =IF(OR(C25<>"",D25<>""),C25-D25,"") | F25: =IF(D25="","",IF(D25>C25,"Over","OK"))
E26: =IF(OR(C26<>"",D26<>""),C26-D26,"") | F26: =IF(D26="","",IF(D26>C26,"Over","OK"))
E27: =IF(OR(C27<>"",D27<>""),C27-D27,"") | F27: =IF(D27="","",IF(D27>C27,"Over","OK"))
E28: =IF(OR(C28<>"",D28<>""),C28-D28,"") | F28: =IF(D28="","",IF(D28>C28,"Over","OK"))
E29: =IF(OR(C29<>"",D29<>""),C29-D29,"") | F29: =IF(D29="","",IF(D29>C29,"Over","OK"))
E30: =IF(OR(C30<>"",D30<>""),C30-D30,"") | F30: =IF(D30="","",IF(D30>C30,"Over","OK"))
E31: =IF(OR(C31<>"",D31<>""),C31-D31,"") | F31: =IF(D31="","",IF(D31>C31,"Over","OK"))
... E34: =IF(OR(C34<>"",D34<>""),C34-D34,"") | F34: =IF(D34="","",IF(D34>C34,"Over","OK"))
A36: Total | C36: =SUM(C5:C34) | D36: =SUM(D5:D34) | E36: =SUM(E5:E34)

Sheet Subscriptions
A1: Subscription tracker
A2: Every recurring charge in one place. Monthly and yearly cost, next renewal, and a keep/cancel call.
G3: Per month | H3: =SUMPRODUCT((F6:F60="Yes")*(E6:E60))
G4: Per year | H4: =H3*12
A5: Service | B5: Cost | C5: Billing | D5: Next renewal | E5: Monthly cost | F5: Keep? | G5: Days to renewal | H5: =SUMPRODUCT((F6:F60="No")*(E6:E60))*12
A6: Spotify | B6: 11.99 | C6: Monthly | E6: =IF(B6="","",IF(C6="Yearly",B6/12,IF(C6="Weekly",B6*52/12,B6))) | F6: Yes | G6: =IF(D6="","",D6-TODAY())
A7: Netflix | B7: 15.49 | C7: Monthly | E7: =IF(B7="","",IF(C7="Yearly",B7/12,IF(C7="Weekly",B7*52/12,B7))) | F7: Yes | G7: =IF(D7="","",D7-TODAY())
A8: iCloud 200GB | B8: 2.99 | C8: Monthly | E8: =IF(B8="","",IF(C8="Yearly",B8/12,IF(C8="Weekly",B8*52/12,B8))) | F8: Yes | G8: =IF(D8="","",D8-TODAY())
A9: Gym | B9: 45 | C9: Monthly | E9: =IF(B9="","",IF(C9="Yearly",B9/12,IF(C9="Weekly",B9*52/12,B9))) | F9: Yes | G9: =IF(D9="","",D9-TODAY())
A10: Adobe Creative Cloud | B10: 59.99 | C10: Monthly | E10: =IF(B10="","",IF(C10="Yearly",B10/12,IF(C10="Weekly",B10*52/12,B10))) | F10: No | G10: =IF(D10="","",D10-TODAY())
A11: Amazon Prime | B11: 139 | C11: Yearly | E11: =IF(B11="","",IF(C11="Yearly",B11/12,IF(C11="Weekly",B11*52/12,B11))) | F11: Yes | G11: =IF(D11="","",D11-TODAY())
A12: Domain renewal | B12: 14 | C12: Yearly | E12: =IF(B12="","",IF(C12="Yearly",B12/12,IF(C12="Weekly",B12*52/12,B12))) | F12: Yes | G12: =IF(D12="","",D12-TODAY())
E13: =IF(B13="","",IF(C13="Yearly",B13/12,IF(C13="Weekly",B13*52/12,B13))) | G13: =IF(D13="","",D13-TODAY())
E14: =IF(B14="","",IF(C14="Yearly",B14/12,IF(C14="Weekly",B14*52/12,B14))) | G14: =IF(D14="","",D14-TODAY())
E15: =IF(B15="","",IF(C15="Yearly",B15/12,IF(C15="Weekly",B15*52/12,B15))) | G15: =IF(D15="","",D15-TODAY())
E16: =IF(B16="","",IF(C16="Yearly",B16/12,IF(C16="Weekly",B16*52/12,B16))) | G16: =IF(D16="","",D16-TODAY())
E17: =IF(B17="","",IF(C17="Yearly",B17/12,IF(C17="Weekly",B17*52/12,B17))) | G17: =IF(D17="","",D17-TODAY())
E18: =IF(B18="","",IF(C18="Yearly",B18/12,IF(C18="Weekly",B18*52/12,B18))) | G18: =IF(D18="","",D18-TODAY())
E19: =IF(B19="","",IF(C19="Yearly",B19/12,IF(C19="Weekly",B19*52/12,B19))) | G19: =IF(D19="","",D19-TODAY())
E20: =IF(B20="","",IF(C20="Yearly",B20/12,IF(C20="Weekly",B20*52/12,B20))) | G20: =IF(D20="","",D20-TODAY())
E21: =IF(B21="","",IF(C21="Yearly",B21/12,IF(C21="Weekly",B21*52/12,B21))) | G21: =IF(D21="","",D21-TODAY())
E22: =IF(B22="","",IF(C22="Yearly",B22/12,IF(C22="Weekly",B22*52/12,B22))) | G22: =IF(D22="","",D22-TODAY())
E23: =IF(B23="","",IF(C23="Yearly",B23/12,IF(C23="Weekly",B23*52/12,B23))) | G23: =IF(D23="","",D23-TODAY())
E24: =IF(B24="","",IF(C24="Yearly",B24/12,IF(C24="Weekly",B24*52/12,B24))) | G24: =IF(D24="","",D24-TODAY())
... E60: =IF(B60="","",IF(C60="Yearly",B60/12,IF(C60="Weekly",B60*52/12,B60))) | G60: =IF(D60="","",D60-TODAY())

Sheet Debt
A1: Debt payoff (avalanche)
A2: List each debt. The sheet orders them by interest rate and estimates your debt-free month from total payments.
F3: Total debt | G3: =SUM(B6:B25)
F4: Total monthly payments | G4: =SUM(D6:D25)
A5: Debt | B5: Balance | C5: APR | D5: Monthly payment | E5: Payoff order | F5: Months left (this debt alone) | G5: =IF(G3=0,0,SUMPRODUCT(B6:B25,C6:C25)/G3)
A6: Credit card | B6: 4200 | C6: 0.2499 | D6: 250 | E6: =IF(B6="","",RANK(C6,$C$6:$C$25,0)) | F6: =IF(OR(B6="",D6=0),"",IF(D6<=B6*C6/12,"Payment too small",ROUNDUP(NPER(C6/12,-D6,B6),0))) | G6: =IF(OR(G3=0,G4=0),"",EDATE(TODAY(),MAX(1,ROUNDUP(NPER(G5/12,-G4,G3),0))))
A7: Car loan | B7: 9800 | C7: 0.069 | D7: 310 | E7: =IF(B7="","",RANK(C7,$C$6:$C$25,0)) | F7: =IF(OR(B7="",D7=0),"",IF(D7<=B7*C7/12,"Payment too small",ROUNDUP(NPER(C7/12,-D7,B7),0)))
A8: Student loan | B8: 15500 | C8: 0.055 | D8: 220 | E8: =IF(B8="","",RANK(C8,$C$6:$C$25,0)) | F8: =IF(OR(B8="",D8=0),"",IF(D8<=B8*C8/12,"Payment too small",ROUNDUP(NPER(C8/12,-D8,B8),0)))
E9: =IF(B9="","",RANK(C9,$C$6:$C$25,0)) | F9: =IF(OR(B9="",D9=0),"",IF(D9<=B9*C9/12,"Payment too small",ROUNDUP(NPER(C9/12,-D9,B9),0)))
E10: =IF(B10="","",RANK(C10,$C$6:$C$25,0)) | F10: =IF(OR(B10="",D10=0),"",IF(D10<=B10*C10/12,"Payment too small",ROUNDUP(NPER(C10/12,-D10,B10),0)))
E11: =IF(B11="","",RANK(C11,$C$6:$C$25,0)) | F11: =IF(OR(B11="",D11=0),"",IF(D11<=B11*C11/12,"Payment too small",ROUNDUP(NPER(C11/12,-D11,B11),0)))
E12: =IF(B12="","",RANK(C12,$C$6:$C$25,0)) | F12: =IF(OR(B12="",D12=0),"",IF(D12<=B12*C12/12,"Payment too small",ROUNDUP(NPER(C12/12,-D12,B12),0)))
E13: =IF(B13="","",RANK(C13,$C$6:$C$25,0)) | F13: =IF(OR(B13="",D13=0),"",IF(D13<=B13*C13/12,"Payment too small",ROUNDUP(NPER(C13/12,-D13,B13),0)))
E14: =IF(B14="","",RANK(C14,$C$6:$C$25,0)) | F14: =IF(OR(B14="",D14=0),"",IF(D14<=B14*C14/12,"Payment too small",ROUNDUP(NPER(C14/12,-D14,B14),0)))
E15: =IF(B15="","",RANK(C15,$C$6:$C$25,0)) | F15: =IF(OR(B15="",D15=0),"",IF(D15<=B15*C15/12,"Payment too small",ROUNDUP(NPER(C15/12,-D15,B15),0)))
E16: =IF(B16="","",RANK(C16,$C$6:$C$25,0)) | F16: =IF(OR(B16="",D16=0),"",IF(D16<=B16*C16/12,"Payment too small",ROUNDUP(NPER(C16/12,-D16,B16),0)))
E17: =IF(B17="","",RANK(C17,$C$6:$C$25,0)) | F17: =IF(OR(B17="",D17=0),"",IF(D17<=B17*C17/12,"Payment too small",ROUNDUP(NPER(C17/12,-D17,B17),0)))
E18: =IF(B18="","",RANK(C18,$C$6:$C$25,0)) | F18: =IF(OR(B18="",D18=0),"",IF(D18<=B18*C18/12,"Payment too small",ROUNDUP(NPER(C18/12,-D18,B18),0)))
E19: =IF(B19="","",RANK(C19,$C$6:$C$25,0)) | F19: =IF(OR(B19="",D19=0),"",IF(D19<=B19*C19/12,"Payment too small",ROUNDUP(NPER(C19/12,-D19,B19),0)))
E20: =IF(B20="","",RANK(C20,$C$6:$C$25,0)) | F20: =IF(OR(B20="",D20=0),"",IF(D20<=B20*C20/12,"Payment too small",ROUNDUP(NPER(C20/12,-D20,B20),0)))
... E25: =IF(B25="","",RANK(C25,$C$6:$C$25,0)) | F25: =IF(OR(B25="",D25=0),"",IF(D25<=B25*C25/12,"Payment too small",ROUNDUP(NPER(C25/12,-D25,B25),0)))

Sheet NetWorth
A1: Net worth
A2: Assets minus debts. Add a row per account; update monthly on the Log tab to see the trend.
C3: Net worth | D3: =SUM(B6:B25)-Debt!G3
A5: Asset | B5: Value | C5: Type
A6: Checking | B6: 2400 | C6: Cash
A7: Savings | B7: 6100 | C7: Cash
A8: 401(k) | B8: 18400 | C8: Retirement
A9: Brokerage | B9: 3200 | C9: Investments

Sheet Log
A1: Monthly log
A2: At the end of each month, copy the Dashboard numbers here. The chart shows your savings rate over time.
A4: Month | B4: Income | C4: Spending | D4: Saved | E4: Savings rate | F4: Net worth
A5: 46023 | D5: =IF(B5="","",B5-C5) | E5: =IF(OR(B5="",B5=0),"",D5/B5)
A6: 46054 | D6: =IF(B6="","",B6-C6) | E6: =IF(OR(B6="",B6=0),"",D6/B6)
A7: 46082 | D7: =IF(B7="","",B7-C7) | E7: =IF(OR(B7="",B7=0),"",D7/B7)
A8: 46113 | D8: =IF(B8="","",B8-C8) | E8: =IF(OR(B8="",B8=0),"",D8/B8)
A9: 46143 | D9: =IF(B9="","",B9-C9) | E9: =IF(OR(B9="",B9=0),"",D9/B9)
A10: 46174 | D10: =IF(B10="","",B10-C10) | E10: =IF(OR(B10="",B10=0),"",D10/B10)
A11: 46204 | D11: =IF(B11="","",B11-C11) | E11: =IF(OR(B11="",B11=0),"",D11/B11)
A12: 46235 | D12: =IF(B12="","",B12-C12) | E12: =IF(OR(B12="",B12=0),"",D12/B12)
A13: 46266 | D13: =IF(B13="","",B13-C13) | E13: =IF(OR(B13="",B13=0),"",D13/B13)
A14: 46296 | D14: =IF(B14="","",B14-C14) | E14: =IF(OR(B14="",B14=0),"",D14/B14)
A15: 46327 | D15: =IF(B15="","",B15-C15) | E15: =IF(OR(B15="",B15=0),"",D15/B15)
A16: 46357 | D16: =IF(B16="","",B16-C16) | E16: =IF(OR(B16="",B16=0),"",D16/B16)
